[
  {
    "text": "T1和BLG就像两座大厦，T1好比大厦A，而BLG就是大厦B，给两队打分的话，T1就是100吧，BLG的话九十几把。",
    "pictures": [],
    "emote_pictures": []
  },
  {
    "text": "[吃瓜]",
    "pictures": [
      "http://i0.hdslb.com/bfs/new_dyn/5e6a45a1f5b1da5746b32e6aec2866c9342034206.jpg"
    ],
    "emote_pictures": [
      "https://i0.hdslb.com/bfs/emote/4191ce3c44c2b3df8fd97c33f85d3ab15f4f3c84.png"
    ]
  },
  {
    "text": "十三连胜",
    "pictures": [],
    "emote_pictures": []
  },
  {
    "text": "经典没AL",
    "pictures": [],
    "emote_pictures": []
  },
  {
    "text": "人太少了，没有李宁和al",
    "pictures": [],
    "emote_pictures": []
  },
  {
    "text": "萌新想问下，连赢13场和连输13场哪个困难点[doge]",
    "pictures": [],
    "emote_pictures": [
      "https://i0.hdslb.com/bfs/emote/3087d273a78ccaff4bb1e9972e2ba2a7583c9f11.png"
    ]
  },
  {
    "text": "oner是有点怕wei的[妙啊]",
    "pictures": [],
    "emote_pictures": [
      "https://i0.hdslb.com/bfs/emote/b4cb77159d58614a9b787b91b1cd22a81f383535.png"
    ]
  },
  {
    "text": "T1哥在这收集队表呢",
    "pictures": [],
    "emote_pictures": []
  },
  {
    "text": "一队虐遍lpl所有队伍，服了服了",
    "pictures": [],
    "emote_pictures": []
  },
  {
    "text": "中国拿高价韩媛就算了，现在更是连教练也一块儿买了，5个人的队伍。两个韩援，一个韩国教练这样拿的冠军你们也认可吗？赚完你的钱，人家也不给中国交税。人家带回韩国花去了，也不在中国花，一个个的还搁那儿支持中国队呢，人家只会拿着你的钱买韩援。反正也是给韩国送钱，直接支持t1不就完了，我已经提前打印6颗星旗子了，见我评论者t1夺冠以后一人100Q币",
    "pictures": [
      "http://i0.hdslb.com/bfs/new_dyn/77189f6c14c9672519fcb946e499afa9536505815.jpg"
    ],
    "emote_pictures": []
  },
  {
    "text": "明年还有热度吗我感觉",
    "pictures": [],
    "emote_pictures": []
  },
  {
    "text": "还真是",
    "pictures": [],
    "emote_pictures": []
  },
  {
    "text": "[妙啊]",
    "pictures": [
      "http://i0.hdslb.com/bfs/new_dyn/c5b2957dff54f06f49f6d1b93ec8886413651668.png"
    ],
    "emote_pictures": [
      "https://i0.hdslb.com/bfs/emote/b4cb77159d58614a9b787b91b1cd22a81f383535.png"
    ]
  },
  {
    "text": "请问还有谁?[笑哭]",
    "pictures": [],
    "emote_pictures": [
      "https://i0.hdslb.com/bfs/emote/c3043ba94babf824dea03ce500d0e73763bf4f40.png"
    ]
  },
  {
    "text": "事实证明，确实是",
    "pictures": [],
    "emote_pictures": []
  },
  {
    "text": "已经结束了",
    "pictures": [],
    "emote_pictures": []
  },
  {
    "text": "这么看来陀螺王应该是奔雷手[妙啊]",
    "pictures": [],
    "emote_pictures": [
      "https://i0.hdslb.com/bfs/emote/b4cb77159d58614a9b787b91b1cd22a81f383535.png"
    ]
  },
  {
    "text": "可惜韩国队最怕的blg签运太差了没能制裁lck，大飞和bdd都有点怕左手的",
    "pictures": [],
    "emote_pictures": []
  },
  {
    "text": "e z",
    "pictures": [],
    "emote_pictures": []
  },
  {
    "text": "常看常新",
    "pictures": [],
    "emote_pictures": []
  }
]