[
  {
    "text": "[doge_金箍]",
    "pictures": [],
    "emote_pictures": [
      "https://i0.hdslb.com/bfs/emote/aadaca1895e09c5596fc6365192ec93a23718cf0.png"
    ]
  },
  {
    "text": "忆惜当年泪不干",
    "pictures": [],
    "emote_pictures": []
  },
  {
    "text": "唉(╥ω╥`)",
    "pictures": [],
    "emote_pictures": []
  },
  {
    "text": "是布偶",
    "pictures": [],
    "emote_pictures": []
  },
  {
    "text": "Scout这时候破败王操作真的惊艳过我，捡的每个英雄都操作得特别好。",
    "pictures": [],
    "emote_pictures": []
  },
  {
    "text": "盗梦空间",
    "pictures": [],
    "emote_pictures": []
  },
  {
    "text": "除了公和枪还有高光表现，其他三个人的风评远不及当年",
    "pictures": [],
    "emote_pictures": []
  },
  {
    "text": "这几个人现在风评都好差，野辅被喷死了，盗，圣枪成油和混了。除了viper都烂完了",
    "pictures": [],
    "emote_pictures": []
  },
  {
    "text": "学弟破败王还真不错",
    "pictures": [],
    "emote_pictures": []
  },
  {
    "text": "寡妇的魅惑不也是控制么？冠军皮肤在佛耶戈背后隐身了[doge]",
    "pictures": [],
    "emote_pictures": [
      "https://i0.hdslb.com/bfs/emote/3087d273a78ccaff4bb1e9972e2ba2a7583c9f11.png"
    ]
  },
  {
    "text": "阵容废物，五个人厉害",
    "pictures": [],
    "emote_pictures": []
  },
  {
    "text": "特效满天飞[喜极而泣]",
    "pictures": [],
    "emote_pictures": [
      "https://i0.hdslb.com/bfs/emote/485a7e0c01c2d70707daae53bee4a9e2e31ef1ed.png"
    ]
  },
  {
    "text": "这套皮肤真的好看",
    "pictures": [],
    "emote_pictures": []
  },
  {
    "text": "回不去的s11五人组",
    "pictures": [],
    "emote_pictures": []
  },
  {
    "text": "再反转，edg的风评进深渊了",
    "pictures": [],
    "emote_pictures": []
  },
  {
    "text": "好好好",
    "pictures": [],
    "emote_pictures": []
  },
  {
    "text": "盗÷进世界赛了，edg呢",
    "pictures": [],
    "emote_pictures": []
  },
  {
    "text": "唉，xqs的奶嘴",
    "pictures": [],
    "emote_pictures": []
  },
  {
    "text": "回不去了",
    "pictures": [],
    "emote_pictures": []
  },
  {
    "text": "唉",
    "pictures": [],
    "emote_pictures": []
  }
]