[
  {
    "text": "你真的是人类吗[难过]",
    "pictures": [],
    "emote_pictures": [
      "https://i0.hdslb.com/bfs/emote/a651db36701610aa70a781fa98c07c9789b11543.png"
    ]
  },
  {
    "text": "byd，我玩了2k+小时都没发现能这么玩",
    "pictures": [],
    "emote_pictures": []
  },
  {
    "text": "玩屁男，把门都堵住，他们来了你还能知道，而且还能乘他们破门时间再多按两下，终于把门破了只会发现你的盒子",
    "pictures": [],
    "emote_pictures": []
  },
  {
    "text": "不愧是玩滋崩的",
    "pictures": [],
    "emote_pictures": []
  },
  {
    "text": "@燎花 @Late1y_ @Tradermid",
    "pictures": [],
    "emote_pictures": []
  },
  {
    "text": "玩原神玩的",
    "pictures": [],
    "emote_pictures": []
  },
  {
    "text": "@阿吧阿吧の0",
    "pictures": [],
    "emote_pictures": []
  },
  {
    "text": "@蓝某胖",
    "pictures": [],
    "emote_pictures": []
  },
  {
    "text": "这局的其他人：我必须立刻马上先把那个玩地图室的初生先干掉",
    "pictures": [
      "http://i0.hdslb.com/bfs/new_dyn/47b27467ee4059d003bf23b9d2b940a197873622.jpg"
    ],
    "emote_pictures": []
  },
  {
    "text": "我就想知道，真的假的，全图能听到吗",
    "pictures": [],
    "emote_pictures": []
  },
  {
    "text": "@GENG_ASIAZXD",
    "pictures": [],
    "emote_pictures": []
  },
  {
    "text": "@xs喵 @天花板上の纱世里酱 @fopzzq @泠雨落枫 @抹尘不加冰",
    "pictures": [],
    "emote_pictures": []
  },
  {
    "text": "这样子会有什么情况吖[鸭科夫_干嘛鸭]",
    "pictures": [],
    "emote_pictures": [
      "https://i0.hdslb.com/bfs/emote/2e67293d703e6501d7a639870477cbcc16277a23.png"
    ]
  },
  {
    "text": "赛博癫笑",
    "pictures": [],
    "emote_pictures": []
  },
  {
    "text": "就玩亿把[doge]",
    "pictures": [],
    "emote_pictures": [
      "https://i0.hdslb.com/bfs/emote/3087d273a78ccaff4bb1e9972e2ba2a7583c9f11.png"
    ]
  },
  {
    "text": "准确的说你只恶心了57人",
    "pictures": [],
    "emote_pictures": []
  },
  {
    "text": "@风风竹一 @天啼 @嘤熊污萎 @突然降温的天气 @纸悠DESPAIR @King风暴",
    "pictures": [],
    "emote_pictures": []
  },
  {
    "text": "不懂就问[笑哭]新人入坑Apex还来得及吗",
    "pictures": [],
    "emote_pictures": [
      "https://i0.hdslb.com/bfs/emote/c3043ba94babf824dea03ce500d0e73763bf4f40.png"
    ]
  },
  {
    "text": "鼠标是迈从M7，耳机epz g20，鼠耳有了，键盘选啥好",
    "pictures": [],
    "emote_pictures": []
  },
  {
    "text": "你这直接跑啊，甩开他们再回来按不是更折磨人",
    "pictures": [],
    "emote_pictures": []
  }
]