[
  {
    "text": "马克龙卸任了来中国当明星了吧，不比那破官儿当的舒服嘛",
    "pictures": [],
    "emote_pictures": [
      "https://gsp0.baidu.com/5aAHeD3nKhI2p27j8IqW0jdnxx1xbK/tb/editor/images/client/image_emoticon22.png",
      "https://gsp0.baidu.com/5aAHeD3nKhI2p27j8IqW0jdnxx1xbK/tb/editor/images/client/image_emoticon22.png",
      "https://gsp0.baidu.com/5aAHeD3nKhI2p27j8IqW0jdnxx1xbK/tb/editor/images/client/image_emoticon22.png"
    ]
  },
  {
    "text": "他在这的表演，其目的也是为了换得国内支持率罢了。",
    "pictures": [],
    "emote_pictures": [
      "https://gsp0.baidu.com/5aAHeD3nKhI2p27j8IqW0jdnxx1xbK/tb/editor/images/client/image_emoticon67.png",
      "https://gsp0.baidu.com/5aAHeD3nKhI2p27j8IqW0jdnxx1xbK/tb/editor/images/client/image_emoticon67.png"
    ]
  },
  {
    "text": "马克龙：我就是为了这碟醋，包了这顿饺子",
    "pictures": [],
    "emote_pictures": []
  },
  {
    "text": "来备份个工业排面拉满点怎么了，这是应该的只有进来的企业民用稀土管够",
    "pictures": [],
    "emote_pictures": [
      "https://gsp0.baidu.com/5aAHeD3nKhI2p27j8IqW0jdnxx1xbK/tb/editor/images/client/image_emoticon25.png",
      "https://gsp0.baidu.com/5aAHeD3nKhI2p27j8IqW0jdnxx1xbK/tb/editor/images/client/image_emoticon25.png",
      "https://gsp0.baidu.com/5aAHeD3nKhI2p27j8IqW0jdnxx1xbK/tb/editor/images/client/image_emoticon25.png"
    ]
  },
  {
    "text": "马的笑",
    "pictures": [],
    "emote_pictures": []
  },
  {
    "text": "为了卖酱油搭了几根面条。。",
    "pictures": [],
    "emote_pictures": []
  },
  {
    "text": "挣钱嘛，跪着不寒颤",
    "pictures": [],
    "emote_pictures": []
  },
  {
    "text": "熟悉的一幕 上次是哪个学校来着",
    "pictures": [],
    "emote_pictures": [
      "https://gsp0.baidu.com/5aAHeD3nKhI2p27j8IqW0jdnxx1xbK/tb/editor/images/client/image_emoticon68.png"
    ]
  },
  {
    "text": "小马哥:拍，记者呢，我带的人呢，给我好好拍，回去怎么宣传不用我说了吧",
    "pictures": [],
    "emote_pictures": [
      "https://gsp0.baidu.com/5aAHeD3nKhI2p27j8IqW0jdnxx1xbK/tb/editor/images/client/image_emoticon6.png"
    ]
  },
  {
    "text": "马克龙怕老婆，来成都正好乎应川渝暴龙，中西结合。",
    "pictures": [],
    "emote_pictures": []
  },
  {
    "text": "后面有两个保镖打起来了，咱跟法国人",
    "pictures": [],
    "emote_pictures": []
  },
  {
    "text": "四川大学是不是那个诬告农民工偷拍的？",
    "pictures": [],
    "emote_pictures": []
  },
  {
    "text": "这可比大熊猫稀罕多了，要我我也去看热闹",
    "pictures": [],
    "emote_pictures": [
      "https://gsp0.baidu.com/5aAHeD3nKhI2p27j8IqW0jdnxx1xbK/tb/editor/images/client/image_emoticon22.png"
    ]
  },
  {
    "text": "别走啦，留下吧。哪的黄土不埋人呢",
    "pictures": [],
    "emote_pictures": [
      "https://tb2.bdstatic.com/tb/editor/images/face/i_f22.png?t=20140803"
    ]
  },
  {
    "text": "去哪不好，去了个川大",
    "pictures": [],
    "emote_pictures": []
  },
  {
    "text": "至少说明大陆是热情有礼的，他来两次都很受欢迎",
    "pictures": [],
    "emote_pictures": []
  },
  {
    "text": "你看他，笑得多开心",
    "pictures": [],
    "emote_pictures": [
      "https://gsp0.baidu.com/5aAHeD3nKhI2p27j8IqW0jdnxx1xbK/tb/editor/images/client/image_emoticon33.png"
    ]
  },
  {
    "text": "开个直播号，国内指定有几百万上千万粉，赚钱也是so easy。",
    "pictures": [],
    "emote_pictures": []
  },
  {
    "text": "大乐子，谁不想看看乐呵乐呵",
    "pictures": [],
    "emote_pictures": [
      "https://gsp0.baidu.com/5aAHeD3nKhI2p27j8IqW0jdnxx1xbK/tb/editor/images/client/image_emoticon22.png"
    ]
  },
  {
    "text": "看猴罢了",
    "pictures": [],
    "emote_pictures": []
  }
]