[
  {
    "text": "看消息称，我们要2027重点具备更强大的登陆力量，看央妈最近报道野牛啥的，年底要例行训练了，说明我们一直在有备无患，狗头镇楼，防止被夹，最近发的帖子太容易被删了",
    "pictures": [
      "http://tiebapic.baidu.com/forum/w%3D580/sign=58fecf578c8065387beaa41ba7dca115/1994e71190ef76c66c02b132db16fdfaae5167a5.jpg?tbpicau=2025-12-19-05_48e295130144864767328aa4a14bf599",
      "http://tiebapic.baidu.com/forum/w%3D580/sign=41cee8f4e744ad342ebf878fe0a30c08/32529d16fdfaaf512333cba6ca5494eef11f7aa5.jpg?tbpicau=2025-12-19-05_303d0b3f472f2c291b96a96f01be35ad"
    ],
    "emote_pictures": [
      "https://gsp0.baidu.com/5aAHeD3nKhI2p27j8IqW0jdnxx1xbK/tb/editor/images/client/image_emoticon2.png",
      "https://gsp0.baidu.com/5aAHeD3nKhI2p27j8IqW0jdnxx1xbK/tb/editor/images/client/image_emoticon9.png"
    ]
  },
  {
    "text": "26年吧",
    "pictures": [],
    "emote_pictures": []
  },
  {
    "text": "等不到27了，看现在形势舆论26很大概率",
    "pictures": [],
    "emote_pictures": [
      "https://gsp0.baidu.com/5aAHeD3nKhI2p27j8IqW0jdnxx1xbK/tb/editor/images/client/image_emoticon68.png"
    ]
  },
  {
    "text": "围台，把他们一切可以联网的都切掉， 不能上网玩游戏他们年轻人马上投降",
    "pictures": [],
    "emote_pictures": [
      "https://gsp0.baidu.com/5aAHeD3nKhI2p27j8IqW0jdnxx1xbK/tb/editor/images/client/image_emoticon16.png"
    ]
  },
  {
    "text": "总感觉明年就够了",
    "pictures": [],
    "emote_pictures": []
  },
  {
    "text": "不需要，现在就足够了。",
    "pictures": [],
    "emote_pictures": []
  },
  {
    "text": "明天就打",
    "pictures": [],
    "emote_pictures": []
  },
  {
    "text": "杀只脚盆鸡，给猴子看看，给同胞庆祝下就好了。",
    "pictures": [],
    "emote_pictures": []
  },
  {
    "text": "把我们描述成为这个地方唯一的坏人，那无非就是要达成“举世伐唐”的局面。",
    "pictures": [],
    "emote_pictures": []
  },
  {
    "text": "可能提前到2026了",
    "pictures": [],
    "emote_pictures": [
      "https://gsp0.baidu.com/5aAHeD3nKhI2p27j8IqW0jdnxx1xbK/tb/editor/images/client/image_emoticon25.png"
    ]
  },
  {
    "text": "每年的四月和十一月都是窗口期台湾海峡的气候条件对军事行动，特别是两栖登陆作战，有直接影响。台湾在每年11月至次年3月盛行东北季风，风浪较大，不利于登陆作战。而3月之后风浪减小，进入相对平稳期。台风季（通常在6月至9月）又会带来强风暴雨，同样不利于大规模军事行动。因此，理论上在季风结束、台风季来临前的窗口期（如9月至11月），气候条件可能相对更有利。部分分析认为，每年可能有3到5个月的“窗口期”，而4月和11月恰好处于或接近这些分析所指的时段。",
    "pictures": [],
    "emote_pictures": []
  },
  {
    "text": "估计不用27年，明年大概率了",
    "pictures": [],
    "emote_pictures": [
      "https://tb2.bdstatic.com/tb/editor/images/face/i_f25.png?t=20140803"
    ]
  },
  {
    "text": "应该还得进行几次大规模合练，现在演习规模相距实战还是太小了，有必要充分验证各部队间的配合能力",
    "pictures": [],
    "emote_pictures": []
  },
  {
    "text": "反正我最近所有分析27的内容都被秒删，有次说的多了还被度娘赏了个7天",
    "pictures": [],
    "emote_pictures": [
      "https://tb2.bdstatic.com/tb/editor/images/face/i_f28.png?t=20140803"
    ]
  },
  {
    "text": "嘿嘿嘿，不是这样，特朗普干嘛急着掏空湾湾啊？",
    "pictures": [],
    "emote_pictures": []
  },
  {
    "text": "一百周年那个节点，有多重要，傻子都知道！",
    "pictures": [],
    "emote_pictures": []
  },
  {
    "text": "快点来吧",
    "pictures": [],
    "emote_pictures": []
  },
  {
    "text": "春节东京省过中国年",
    "pictures": [],
    "emote_pictures": []
  },
  {
    "text": "没那么慢，特种作战前几年就开始练了",
    "pictures": [],
    "emote_pictures": []
  },
  {
    "text": "27年建军100年，懂的都懂",
    "pictures": [],
    "emote_pictures": []
  }
]