[
  {
    "text": "faker只能去捡chovy不要的垃圾？是不是说明在职业选手眼里faker不如chovy一根？",
    "pictures": [
      "http://tiebapic.baidu.com/forum/w%3D580/sign=53b97ceb3ad98d1076d40c39113eb807/0ce39b23720e0cf3aaaea4ec4c46f21fbf09aafb.jpg?tbpicau=2025-12-16-05_49ea9e03e5de183d73224f3b26804b4c"
    ],
    "emote_pictures": []
  },
  {
    "text": "name",
    "pictures": [],
    "emote_pictures": []
  },
  {
    "text": "Her name plz",
    "pictures": [],
    "emote_pictures": []
  },
  {
    "text": "这么经典的老番都没看过，黑-暗-圣-经啊",
    "pictures": [],
    "emote_pictures": []
  },
  {
    "text": "没冠军啊",
    "pictures": [],
    "emote_pictures": [
      "https://gsp0.baidu.com/5aAHeD3nKhI2p27j8IqW0jdnxx1xbK/tb/editor/images/client/image_emoticon22.png"
    ]
  },
  {
    "text": "你猜去年8884844和尺狗为啥降薪也要求签长约？",
    "pictures": [],
    "emote_pictures": []
  },
  {
    "text": "顶级选手想和大超一起8884844了",
    "pictures": [],
    "emote_pictures": []
  },
  {
    "text": "又有钱拿又能打兄弟lol，队伍配置年年银河战舰，傻子才不想和chovy做队友",
    "pictures": [],
    "emote_pictures": []
  },
  {
    "text": "可以这样，第三赛段前跟chovy抱团，后面跟飞哥抱团，这样除了一个联赛冠军，其他都大概率拿下",
    "pictures": [],
    "emote_pictures": []
  },
  {
    "text": "大超一年就几天不同意，就说今年上半年，大超算是最C的了，三姆斯混成这样都能慢慢补齐大满贯拼图，s赛发不发力都无所谓，反正大超会同意，你是三姆斯你想不想和大超打比赛？差不多一整年刷刷野就能吃大合同，闲暇之余还能打打斗魂（PS：大超不仅联赛内夸张，斗魂甚至下棋吃鸡率都很高）",
    "pictures": [],
    "emote_pictures": []
  },
  {
    "text": "经典老番yyds",
    "pictures": [],
    "emote_pictures": []
  },
  {
    "text": "因为大李狗是cjb",
    "pictures": [],
    "emote_pictures": []
  },
  {
    "text": "先降薪和超威拿联赛冠军和mis，再去T1降薪和大飞拿s冠",
    "pictures": [],
    "emote_pictures": [
      "https://gsp0.baidu.com/5aAHeD3nKhI2p27j8IqW0jdnxx1xbK/tb/editor/images/client/image_emoticon24.png"
    ]
  },
  {
    "text": "doran和pezy都是世界赛打得烂，被大超一脚踢出大门的，明年gen打t1好看咯",
    "pictures": [],
    "emote_pictures": []
  },
  {
    "text": "夺冠了就嫌队友菜了",
    "pictures": [],
    "emote_pictures": [
      "https://gsp0.baidu.com/5aAHeD3nKhI2p27j8IqW0jdnxx1xbK/tb/editor/images/client/image_emoticon16.png"
    ]
  },
  {
    "text": "队伍氛围好不会被开卡车，能拿的钱多还能一年赢十一个月",
    "pictures": [],
    "emote_pictures": []
  },
  {
    "text": "你超威爹现在应该在幻想明年逼宫Gen.G买ONER了",
    "pictures": [],
    "emote_pictures": [
      "https://gsp0.baidu.com/5aAHeD3nKhI2p27j8IqW0jdnxx1xbK/tb/editor/images/client/image_emoticon22.png"
    ]
  },
  {
    "text": "原来GG没冠军的选手叫顶级选手，而大飞身边两连冠，三连冠的选手叫剩下的垃圾吗？那很垃圾了",
    "pictures": [],
    "emote_pictures": [
      "https://gsp0.baidu.com/5aAHeD3nKhI2p27j8IqW0jdnxx1xbK/tb/editor/images/client/image_emoticon22.png"
    ]
  },
  {
    "text": "又开始吹超出了",
    "pictures": [],
    "emote_pictures": [
      "https://gsp0.baidu.com/5aAHeD3nKhI2p27j8IqW0jdnxx1xbK/tb/editor/images/client/image_emoticon22.png"
    ]
  },
  {
    "text": "神中神",
    "pictures": [],
    "emote_pictures": []
  }
]