[
  {
    "text": "那我能不能拿下面这张图说泰姆斯其实打不过zeka啊？平心而论，blg打hle那个bo5最大功臣一定是bin，把把对线打着打着就领先2k，一打二换一个doran，全方位完爆doran，但你批售怎么好意思说elk是蹭你批售局势的？我寻思你对线也没打爆zeka啊？你泰姆斯有塞拉斯游龙集锦，那elk也有卡莎一打三集锦啊，而且局势比你那个更险峻，难度更高",
    "pictures": [
      "http://tiebapic.baidu.com/forum/w%3D580/sign=3deeeae53ad98d1076d40c39113fb807/0ce39b23720e0cf3c4f932e24c46f21fbf09aacb.jpg?tbpicau=2025-12-16-05_3ef9938adf5b22ccf55930d769748198",
      "http://tiebapic.baidu.com/forum/w%3D580/sign=be9c67f4e5cc7cd9fa2d34d109012104/954693539822720e1ec09ee33dcb0a46f31fabcb.jpg?tbpicau=2025-12-16-05_4f6abb6037e176f5bbcbf6fa8564534e",
      "http://tiebapic.baidu.com/forum/w%3D580/sign=c4dc3f200d36acaf59e096f44cd98d03/d3fb23a5462309f79f61d10b340e0cf3d6cad6cb.jpg?tbpicau=2025-12-16-05_668de192fafce3db0d1e205513c666da"
    ],
    "emote_pictures": [
      "https://gsp0.baidu.com/5aAHeD3nKhI2p27j8IqW0jdnxx1xbK/tb/editor/images/client/image_emoticon8.png"
    ]
  },
  {
    "text": "我寻思23年blg也没有太守，国际赛照样把韩国队打趴下，jdg到底给lpl带来什么东西？唯一一个国际赛荣誉还是内战拿的，亚运会还因为jdg培养的大韩双c被拿了金牌，胎守这飞舞s赛打bdd对线都被压着打还要靠尺子兜底才能赢，这个b本质上还是那个顺风无限上嘴脸，逆风站不出来的懦守",
    "pictures": [],
    "emote_pictures": []
  },
  {
    "text": "再说一个，第四把小火龙20分钟212刀结果层数才172，全场补刀断档第一，胎盘是怎么好意思甩锅elk抢太守兵线才导致太守叠层慢？建议去看看今年奶油打太守加里奥的补刀层数对比，纯是太守自己熟练度低不会叠层导致层数永远落后一大截",
    "pictures": [
      "http://tiebapic.baidu.com/forum/w%3D580/sign=c275b1f59700baa1ba2c47b37710b9b1/1984e6dce71190ef2b8eeec6881b9d16fcfa60e0.jpg?tbpicau=2025-12-16-05_519e6ab6a768e3fa74432a0a3aef2ca5"
    ],
    "emote_pictures": [
      "https://gsp0.baidu.com/5aAHeD3nKhI2p27j8IqW0jdnxx1xbK/tb/editor/images/client/image_emoticon22.png"
    ]
  },
  {
    "text": "第四把最大的锅肯定是野辅，为什么那一波塞拉斯冲脸没有控住呢？两个人用几个控制控不住一个塞拉斯啊？ 控住塞拉斯，大飞就是纯松那一波塞拉斯死了，节奏断档了之后只要往后拖，blg有很大机会",
    "pictures": [],
    "emote_pictures": []
  },
  {
    "text": "叫什么叫 blg打微博看哪个小人露馅",
    "pictures": [],
    "emote_pictures": []
  },
  {
    "text": "不把锅全推到离队的人身上，blc怎么吹他手碟的统治力。过段时间blg成绩一差，白月光派又会跳出来说bekxo是最好的组合，这点和蝌蚪不遑多让",
    "pictures": [],
    "emote_pictures": []
  },
  {
    "text": "胎盘冷处理了",
    "pictures": [],
    "emote_pictures": [
      "https://gsp0.baidu.com/5aAHeD3nKhI2p27j8IqW0jdnxx1xbK/tb/editor/images/client/image_emoticon1.png"
    ]
  },
  {
    "text": "24年blg打韩华全员gap了，第一把之后韩华被当池袋打，elk和左手都有发挥，反倒是我觉得viper那场根本不行",
    "pictures": [],
    "emote_pictures": []
  },
  {
    "text": "吸氧第四把的女枪被当陀螺抽，玩的像是池袋",
    "pictures": [],
    "emote_pictures": []
  },
  {
    "text": "第一把Zeka上来就把胎手打爆了，后面就发病不当人拿狐狸",
    "pictures": [],
    "emote_pictures": []
  },
  {
    "text": "尿罐子还在装，尿骚味我在外面都闻到了",
    "pictures": [],
    "emote_pictures": []
  },
  {
    "text": "斌割太厉害了，要是当年我打的是马头就好了",
    "pictures": [],
    "emote_pictures": []
  },
  {
    "text": "那个bo5zeka打得挺好的我记得，肯定是hle那边打得最好的",
    "pictures": [],
    "emote_pictures": []
  },
  {
    "text": "本来这两年blg外战能赢就是因为bin强，bin是历史上唯一一个能单线突破韩国强队的单人线，历史唯一没有之一。我早说了多兰之前也是倒霉，每次外战都是遇到bin，其他人根本给不到他这么大压力，今年没有bin，果然多兰都开始游龙了。至于太守，你吹他联赛行，世界赛就完全是蹭局势的，队友没优势，太守一辈子站不出来。不然为啥这么多次世界赛就支楞了24那一年，第一把他bin跌没优势的时候，太守不还是被zeka打的抱头鼠窜",
    "pictures": [],
    "emote_pictures": [
      "https://gsp0.baidu.com/5aAHeD3nKhI2p27j8IqW0jdnxx1xbK/tb/editor/images/client/image_emoticon22.png"
    ]
  },
  {
    "text": "感觉那场都有发挥啊，老喷来喷去的",
    "pictures": [],
    "emote_pictures": []
  },
  {
    "text": "23没太守不也给gg吊起来打",
    "pictures": [],
    "emote_pictures": [
      "https://gsp0.baidu.com/5aAHeD3nKhI2p27j8IqW0jdnxx1xbK/tb/editor/images/client/image_emoticon8.png"
    ]
  },
  {
    "text": "第四把现在风评一直是小人上路炸弹人送了波启动，我力竭那把小人确实贪，但是启动那点钱跟中路塞拉斯那波游龙关系很大吗",
    "pictures": [],
    "emote_pictures": []
  },
  {
    "text": "满足了我对小人的一切幻想",
    "pictures": [],
    "emote_pictures": []
  },
  {
    "text": "小人闹麻，明年等着原形毕露",
    "pictures": [],
    "emote_pictures": []
  },
  {
    "text": "第四把中路洛被塞拉斯e的时候rw再e回队友根本就开不起来，谁没锅呢",
    "pictures": [],
    "emote_pictures": []
  }
]