[
  {
    "text": "把钢笔的生命值删了，攻击力改成暴击率效果原封不动绝对一堆ad出这效果又限制前三次又砍暴击伤害的，哪个ad需要你这三次暴击了？加暴击率还必定暴击，搁这左右脑互搏呢？给老鼠定制装备呢？",
    "pictures": [
      "http://tiebapic.baidu.com/forum/w%3D580/sign=896d85f4a11190ef01fb92d7fe1b9df7/cdbedaf8d72a60592975b4036e34349b023bbaf0.jpg?tbpicau=2025-12-16-05_97ebd1074164cf771eed831eb491822a"
    ],
    "emote_pictures": []
  },
  {
    "text": "你的段位是",
    "pictures": [],
    "emote_pictures": [
      "https://gsp0.baidu.com/5aAHeD3nKhI2p27j8IqW0jdnxx1xbK/tb/editor/images/client/image_emoticon15.png"
    ]
  },
  {
    "text": "老鼠出这个 岂不是无敌了！ 适合老鼠 云阿娜之类的射手",
    "pictures": [],
    "emote_pictures": []
  },
  {
    "text": "这个搭配丛刃不是无敌了，VN一个翻滚梆梆邦三箭谁顶得住，哦，乌兹要回来了吗",
    "pictures": [],
    "emote_pictures": []
  },
  {
    "text": "给孙权嘎嘎扇",
    "pictures": [],
    "emote_pictures": []
  },
  {
    "text": "钢臂不是给战士出的吗？",
    "pictures": [],
    "emote_pictures": []
  },
  {
    "text": "老鼠/泽丽/霞/",
    "pictures": [],
    "emote_pictures": []
  },
  {
    "text": "我想问一下，大嘴和飞机这类出适合吗",
    "pictures": [],
    "emote_pictures": []
  },
  {
    "text": "cd呢，没cd那大招不值钱的ad不是爽翻了，什么大嘴 飞机",
    "pictures": [],
    "emote_pictures": []
  },
  {
    "text": "暴击了给10真伤，怎么就左右脑了",
    "pictures": [],
    "emote_pictures": [
      "https://gsp0.baidu.com/5aAHeD3nKhI2p27j8IqW0jdnxx1xbK/tb/editor/images/client/image_emoticon8.png"
    ]
  },
  {
    "text": "这东西对比的是火炮/讯刃/绿叉/飓风这种装备。感觉数值给够的前提下暴击流VN/云阿纳/特定阵容的老鼠/泽丽都可以考虑出",
    "pictures": [],
    "emote_pictures": []
  },
  {
    "text": "又一个教设计师玩游戏的？",
    "pictures": [
      "http://tiebapic.baidu.com/forum/w%3D580/sign=41e4e2235fd8bc3ec60806c2b28aa6c8/4c130ff531adcbef5b6c291feaaf2edda2cc9f85.jpg?tbpicau=2025-12-16-05_8522eaa9cb6af5a2490b96b2bb275420"
    ],
    "emote_pictures": []
  },
  {
    "text": "大招后百暴有没有CD的？没有的话飞机爽死。",
    "pictures": [],
    "emote_pictures": []
  },
  {
    "text": "Adc就不应该加血量",
    "pictures": [],
    "emote_pictures": []
  },
  {
    "text": "蛮狗无敌了",
    "pictures": [],
    "emote_pictures": []
  },
  {
    "text": "乱斗自爆暴击鼠可以出",
    "pictures": [],
    "emote_pictures": []
  },
  {
    "text": "亚索无敌了",
    "pictures": [
      "http://tiebapic.baidu.com/forum/w%3D580/sign=bccfb229fca1cd1105b672288912c8b0/796ce41090ef76c6e3fcad32db16fdfaaf51672b.jpg?tbpicau=2025-12-16-05_fa9b12adb64c39e00c9820a431231a6c"
    ],
    "emote_pictures": []
  },
  {
    "text": "一眼飞机专属",
    "pictures": [],
    "emote_pictures": []
  },
  {
    "text": "飞机需要终极极速，而且飞机前两件经常是0暴击，相对别的ad缺暴击几率",
    "pictures": [],
    "emote_pictures": []
  },
  {
    "text": "说实话以后就是攻速四件里最多选一个（讯刃 火炮 分裂 新装备）不可能出两件纯攻速的，还是有ad能出的，比如老鼠，霞我感觉还是讯刃，其他不好说，纯脑测",
    "pictures": [],
    "emote_pictures": []
  }
]