[
  {
    "text": "16g以上的pro版和pm抢了4天了，都是秒没，手里的果13真的忍不了了！丐版一直有货，而且秒发货，实在不行换丐版算了？",
    "pictures": [
      "http://tiebapic.baidu.com/forum/w%3D580/sign=012f78848def76093c0b99971edca301/fd08f400baa1cd117f500e39ff12c8fcc2ce2d1c.jpg?tbpicau=2025-12-19-05_91229a57688f3aef990d3b316436f998"
    ],
    "emote_pictures": [
      "https://gsp0.baidu.com/5aAHeD3nKhI2p27j8IqW0jdnxx1xbK/tb/editor/images/client/image_emoticon16.png"
    ]
  },
  {
    "text": "差不少，这代9030提升还是挺大的，",
    "pictures": [],
    "emote_pictures": [
      "https://gsp0.baidu.com/5aAHeD3nKhI2p27j8IqW0jdnxx1xbK/tb/editor/images/client/image_emoticon16.png"
    ]
  },
  {
    "text": "差很多",
    "pictures": [],
    "emote_pictures": []
  },
  {
    "text": "主要是屏幕的差距 你线下看了PM压根不想要标准。处理器讲真不玩游戏无所谓",
    "pictures": [],
    "emote_pictures": []
  },
  {
    "text": "建议过两周，线下就应该都有了",
    "pictures": [],
    "emote_pictures": []
  },
  {
    "text": "建议上promax，pro更难抢",
    "pictures": [],
    "emote_pictures": []
  },
  {
    "text": "目前看大嘴说的提升百分之四十没瞎说",
    "pictures": [],
    "emote_pictures": []
  },
  {
    "text": "抢12g的Pro版",
    "pictures": [],
    "emote_pictures": []
  },
  {
    "text": "差很多，9030pro才能用",
    "pictures": [],
    "emote_pictures": []
  },
  {
    "text": "差很多，现在将就了将来后悔更难受",
    "pictures": [],
    "emote_pictures": []
  },
  {
    "text": "抢到了但是不发货，能怎么办",
    "pictures": [
      "http://tiebapic.baidu.com/forum/w%3D580/sign=0f9df5e33dcb0a4685228b315b62f63e/f60a918f8c5494eef37118006bf5e0fe98257eaf.jpg?tbpicau=2025-12-19-05_41917760b5f983271802845a91030d1c"
    ],
    "emote_pictures": [
      "https://gsp0.baidu.com/5aAHeD3nKhI2p27j8IqW0jdnxx1xbK/tb/editor/images/client/image_emoticon9.png"
    ]
  },
  {
    "text": "看拆解，三款内部电路板完全不一样，不只是芯片不同",
    "pictures": [],
    "emote_pictures": []
  },
  {
    "text": "到下线预订吧，这次pm C/P太高了，相对水果pm而言",
    "pictures": [],
    "emote_pictures": []
  },
  {
    "text": "真想买 预定呗，急啥，离过年还有2个多月.",
    "pictures": [],
    "emote_pictures": []
  },
  {
    "text": "pm 最值得买",
    "pictures": [],
    "emote_pictures": []
  },
  {
    "text": "差非常多",
    "pictures": [],
    "emote_pictures": []
  },
  {
    "text": "制程限制提升应该不大",
    "pictures": [],
    "emote_pictures": []
  },
  {
    "text": "哪位兄弟好心帮我@下那个在2楼和我逼逼赖赖的废物，",
    "pictures": [
      "http://tiebapic.baidu.com/forum/w%3D580/sign=d75456bc4c7b02080cc93fe952d9f25f/d57629f431adcbefcf5b001feaaf2edda2cc9f94.jpg?tbpicau=2025-12-19-05_4705072645a401bd2957bde920ea4db2"
    ],
    "emote_pictures": []
  },
  {
    "text": "性能差不少 但价格差也大 9020够用 日常也流畅丝滑 王者随便玩",
    "pictures": [],
    "emote_pictures": []
  },
  {
    "text": "差挺多 最好是pm以上",
    "pictures": [],
    "emote_pictures": []
  }
]