[
  {
    "text": "@吾名-吾名",
    "pictures": [],
    "emote_pictures": []
  },
  {
    "text": "这黑铁枪感觉稳的一批[笑哭]",
    "pictures": [],
    "emote_pictures": [
      "https://i0.hdslb.com/bfs/emote/c3043ba94babf824dea03ce500d0e73763bf4f40.png"
    ]
  },
  {
    "text": "bug比cf手游少[doge]",
    "pictures": [],
    "emote_pictures": [
      "https://i0.hdslb.com/bfs/emote/3087d273a78ccaff4bb1e9972e2ba2a7583c9f11.png"
    ]
  },
  {
    "text": "端游手游HD都有飓风危城这地图啊，咋会不认识",
    "pictures": [],
    "emote_pictures": []
  },
  {
    "text": "mc还是好玩，啥模式和不同游戏都能玩到各种各样的mod",
    "pictures": [],
    "emote_pictures": []
  },
  {
    "text": "@坏小叽",
    "pictures": [],
    "emote_pictures": []
  },
  {
    "text": "游戏地图名字叫啥",
    "pictures": [],
    "emote_pictures": []
  },
  {
    "text": "66666666666666666666666666666666666666666666666666666",
    "pictures": [],
    "emote_pictures": []
  },
  {
    "text": "感觉明哥像老白一样特别像",
    "pictures": [],
    "emote_pictures": []
  },
  {
    "text": "还有我，我也是来蹭经验值的，哈哈哈哈",
    "pictures": [],
    "emote_pictures": []
  },
  {
    "text": "@穿越火线",
    "pictures": [],
    "emote_pictures": []
  },
  {
    "text": "不是戈门，你这给我干哪儿来了？这还是喜爱福吗？[笑哭][笑哭][笑哭]",
    "pictures": [],
    "emote_pictures": [
      "https://i0.hdslb.com/bfs/emote/c3043ba94babf824dea03ce500d0e73763bf4f40.png"
    ]
  },
  {
    "text": "。1",
    "pictures": [],
    "emote_pictures": []
  },
  {
    "text": "这做的是真离谱啊，超还原",
    "pictures": [],
    "emote_pictures": []
  },
  {
    "text": "1p视角不错呀[doge]",
    "pictures": [],
    "emote_pictures": [
      "https://i0.hdslb.com/bfs/emote/3087d273a78ccaff4bb1e9972e2ba2a7583c9f11.png"
    ]
  },
  {
    "text": "直接收购，你这简直就是，锡林郭勒！[吃瓜]",
    "pictures": [],
    "emote_pictures": [
      "https://i0.hdslb.com/bfs/emote/4191ce3c44c2b3df8fd97c33f85d3ab15f4f3c84.png"
    ]
  },
  {
    "text": "搞一下给这地图搞没",
    "pictures": [],
    "emote_pictures": []
  },
  {
    "text": "看着比cf流畅",
    "pictures": [],
    "emote_pictures": []
  },
  {
    "text": "你给我看的血压飙升[笑哭]",
    "pictures": [],
    "emote_pictures": [
      "https://i0.hdslb.com/bfs/emote/c3043ba94babf824dea03ce500d0e73763bf4f40.png"
    ]
  },
  {
    "text": "明哥你武器在最下面那一行，黄色的",
    "pictures": [],
    "emote_pictures": []
  }
]